{"deviceType":"phone","buildMode":"debug","note":"false","logLevel":"3","isPreview":"true","checkEntry":"true","port":"29905","localPropertiesPath":"E:\\project\\X_hub\\local.properties","Path":"D:\\Program Files\\Huawei\\DevEco Studio\\tools\\node\\","aceProfilePath":"E:\\project\\X_hub\\entry\\.preview\\default\\intermediates\\res\\default\\resources\\base\\profile","hapMode":"false","img2bin":"true","projectProfilePath":"E:\\project\\X_hub\\build-profile.json5","watchMode":"true","appResource":"E:\\project\\X_hub\\entry\\.preview\\default\\intermediates\\res\\default\\ResourceTable.txt","aceBuildJson":"E:\\project\\X_hub\\entry\\.preview\\default\\intermediates\\loader\\default\\loader.json","aceModuleRoot":"E:\\project\\X_hub\\entry\\src\\main\\ets","aceSoPath":"E:\\project\\X_hub\\entry\\.preview\\cache\\nativeDependencies.txt","cachePath":"E:\\project\\X_hub\\entry\\.preview\\cache\\.default","aceModuleBuild":"E:\\project\\X_hub\\entry\\.preview\\default\\intermediates\\assets\\default\\ets","aceModuleJsonPath":"E:\\project\\X_hub\\entry\\.preview\\default\\intermediates\\res\\default\\module.json","stageRouterConfig":{"paths":["E:\\project\\X_hub\\entry\\.preview\\default\\intermediates\\res\\default\\module.json","E:\\project\\X_hub\\entry\\.preview\\default\\intermediates\\res\\default\\resources\\base\\profile\\main_pages.json"],"contents":["{\"module\":{\"pages\":\"$profile:main_pages\",\"name\":\"entry\"}}","{\"src\":[\"pages/Index\",\"pages/VideoList\",\"pages/Player\"]}"]}}